PYSimultanRadiation/__init__.py
PYSimultanRadiation/config.py
PYSimultanRadiation/db_utils.py
PYSimultanRadiation/foi.py
PYSimultanRadiation/ftp_utils.py
PYSimultanRadiation/logger.py
PYSimultanRadiation/shading_analysis.py
PYSimultanRadiation/utils.py
PYSimultanRadiation/view_factor_analysis.py
PYSimultanRadiation/weather.py
PYSimultanRadiation/client/__init__.py
PYSimultanRadiation/client/client.py
PYSimultanRadiation/client/resources/__init__.py
PYSimultanRadiation/client/resources/private_keys/__init__.py
PYSimultanRadiation/client/resources/public_keys/__init__.py
PYSimultanRadiation/docker/__init__.py
PYSimultanRadiation/docker/configs.py
PYSimultanRadiation/docker/docker_manager.py
PYSimultanRadiation/docker/resources/__init__.py
PYSimultanRadiation/docker/resources/docker-compose_db.yml
PYSimultanRadiation/docker/resources/docker-compose_shading.yml
PYSimultanRadiation/docker/resources/docker-compose_template.yml
PYSimultanRadiation/docker/resources/docker-compose_view_factor.yml
PYSimultanRadiation/docker/resources/server_config.yml
PYSimultanRadiation/docker/resources/worker_config.yml
PYSimultanRadiation/docker/resources/__pycache__/__init__.cpython-38.pyc
PYSimultanRadiation/docker/resources/database/__init__.py
PYSimultanRadiation/geometry/__init__.py
PYSimultanRadiation/geometry/base_geometry.py
PYSimultanRadiation/geometry/extended_default_types.py
PYSimultanRadiation/geometry/extended_geometry.py
PYSimultanRadiation/geometry/scene.py
PYSimultanRadiation/geometry/utils.py
PYSimultanRadiation/gui/__init__.py
PYSimultanRadiation/gui/dialogs.py
PYSimultanRadiation/gui/login_frame.py
PYSimultanRadiation/gui/main_window.py
PYSimultanRadiation/radiation/__init__.py
PYSimultanRadiation/radiation/geometry.py
PYSimultanRadiation/radiation/location.py
PYSimultanRadiation/radiation/scene.py
PYSimultanRadiation/radiation/utils.py
PYSimultanRadiation/resources/__init__.py
PYSimultanRadiation/resources/project_loader_template.yml
PySimultanRadiation-0.0.16.dist-info/LICENSE.txt
PySimultanRadiation-0.0.16.dist-info/METADATA
PySimultanRadiation-0.0.16.dist-info/WHEEL
PySimultanRadiation-0.0.16.dist-info/entry_points.txt
PySimultanRadiation-0.0.16.dist-info/top_level.txt
PySimultanRadiation-0.0.16.dist-info/RECORD
